{"cameraMode":{"drawMode":0,"name":"Shaded","section":"Shading Mode"},"sceneLighting":true,"audioPlay":false,"sceneViewState":{"m_AlwaysRefresh":false,"showFog":true,"showSkybox":true,"showFlares":true,"showImageEffects":true,"showParticleSystems":true,"showVisualEffectGraphs":true,"m_FxEnabled":true},"in2DMode":false,"pivot":{"x":0.6344471573829651,"y":4.8411030769348148,"z":-2.8194475173950197},"rotation":{"x":-0.12672048807144166,"y":-0.18427658081054688,"z":0.023909088224172593,"w":-0.9744164943695068},"size":0.8660253882408142,"orthographic":false}